data_quality_validator/__init__.py
data_quality_validator/validator.py
data_quality_validator-0.1.0.dist-info/LICENSE
data_quality_validator-0.1.0.dist-info/METADATA
data_quality_validator-0.1.0.dist-info/WHEEL
data_quality_validator-0.1.0.dist-info/top_level.txt
data_quality_validator-0.1.0.dist-info/RECORD
